stor/__init__.py
stor/base.py
stor/cli.py
stor/default.cfg
stor/default.env
stor/dx.py
stor/exceptions.py
stor/extensions/__init__.py
stor/extensions/swiftstack.py
stor/obs.py
stor/posix.py
stor/s3.py
stor/settings.py
stor/stor-completion.bash
stor/swift.py
stor/test.py
stor/tests/__init__.py
stor/tests/cassettes_py3/TestCanonicalProject/test_canonical_path.yaml
stor/tests/cassettes_py3/TestCanonicalProject/test_canonical_path_on_dir.yaml
stor/tests/cassettes_py3/TestCanonicalProject/test_duplicate_projects.yaml
stor/tests/cassettes_py3/TestCanonicalProject/test_no_project.yaml
stor/tests/cassettes_py3/TestCanonicalProject/test_unique_project.yaml
stor/tests/cassettes_py3/TestCanonicalResource/test_duplicate_resource.yaml
stor/tests/cassettes_py3/TestCanonicalResource/test_no_resource.yaml
stor/tests/cassettes_py3/TestCanonicalResource/test_project.yaml
stor/tests/cassettes_py3/TestCanonicalResource/test_unique_resource.yaml
stor/tests/cassettes_py3/TestCanonicalResource/test_virtual_on_virtual.yaml
stor/tests/cassettes_py3/TestCopy/test_clone_move_project_fail.yaml
stor/tests/cassettes_py3/TestCopy/test_clone_within_project_fail.yaml
stor/tests/cassettes_py3/TestCopy/test_dx_canonical_to_dx_file.yaml
stor/tests/cassettes_py3/TestCopy/test_dx_dir_to_posix_error.yaml
stor/tests/cassettes_py3/TestCopy/test_dx_to_dx_diff_project_exist_file.yaml
stor/tests/cassettes_py3/TestCopy/test_dx_to_dx_file.yaml
stor/tests/cassettes_py3/TestCopy/test_dx_to_dx_file_folder_no_ext.yaml
stor/tests/cassettes_py3/TestCopy/test_dx_to_dx_folder.yaml
stor/tests/cassettes_py3/TestCopy/test_dx_to_dx_same_project_exist_dest.yaml
stor/tests/cassettes_py3/TestCopy/test_dx_to_dx_within_project_fail.yaml
stor/tests/cassettes_py3/TestCopy/test_dx_to_dx_within_project_pass.yaml
stor/tests/cassettes_py3/TestCopy/test_dx_to_other_obs.yaml
stor/tests/cassettes_py3/TestCopy/test_dx_to_posix_file.yaml
stor/tests/cassettes_py3/TestCopy/test_dx_to_posix_file_folder_no_ext.yaml
stor-4.1.1.dist-info/entry_points.txt
stor-4.1.1.dist-info/LICENSE
stor-4.1.1.dist-info/WHEEL
stor-4.1.1.dist-info/METADATA
stor-4.1.1.dist-info/RECORD
