Metadata-Version: 2.1
Name: stor
Version: 4.1.1
Summary: Cross-compatible API for accessing Posix and OBS storage systems
Home-page: https://counsyl.github.io/stor
License: MIT
Author: Counsyl Inc.
Author-email: opensource@counsyl.com
Requires-Python: >=3.6,<4.0
Classifier: Development Status :: 5 - Production/Stable
Classifier: Intended Audience :: Developers
Classifier: License :: OSI Approved :: MIT License
Classifier: Operating System :: OS Independent
Classifier: Programming Language :: Python :: 3
Classifier: Programming Language :: Python :: 3.6
Classifier: Programming Language :: Python :: 3.7
Classifier: Programming Language :: Python :: 3.8
Requires-Dist: boto3 (>=1.7.0)
Requires-Dist: cached-property (>=1.5.1)
Requires-Dist: dxpy (>=0.278.0)
Requires-Dist: python-keystoneclient (>=1.8.1)
Requires-Dist: python-swiftclient (>=3.6.0)
Requires-Dist: requests (>=2.20.0)
Project-URL: Repository, https://github.com/counsyl/stor
